{
  "type": "Feature",
  "properties": {
    "gn:admin1_code":"0.0",
    "gn:asciiname":"Belle Hill",
    "gn:country_code":"MF",
    "gn:dem":15,
    "gn:feature_class":"P",
    "gn:feature_code":"PPLL",
    "gn:name":"Belle Hill",
    "gn:population":0,
    "gn:timezone":"America/Marigot",
    "iso:country":"MF",
    "name:fra_x_preferred":[
        "Belle Hill"
    ],
    "wof:name":"Belle Hill",
    "wof:placetype":"locality"
},
  "geometry": {"coordinates":[-63.05217,18.11031],"type":"Point"}
}