{
  "type": "Feature",
  "properties": {
    "gn:admin1_code":"0.0",
    "gn:asciiname":"Les Jardins D'Orient Bay",
    "gn:country_code":"MF",
    "gn:dem":63,
    "gn:feature_class":"P",
    "gn:feature_code":"PPLL",
    "gn:name":"Les Jardins D\u2019Orient Bay",
    "gn:population":0,
    "gn:timezone":"America/Marigot",
    "iso:country":"MF",
    "wof:name":"Les Jardins D'Orient Bay",
    "wof:placetype":"locality"
},
  "geometry": {"coordinates":[-63.03059,18.08668],"type":"Point"}
}