{
  "type": "Feature",
  "properties": {
    "gn:admin1_code":"0.0",
    "gn:asciiname":"Embouchure",
    "gn:country_code":"MF",
    "gn:dem":1,
    "gn:feature_class":"P",
    "gn:feature_code":"PPLL",
    "gn:name":"Embouchure",
    "gn:population":0,
    "gn:timezone":"America/Marigot",
    "iso:country":"MF",
    "name:fra_x_preferred":[
        "Embouchure"
    ],
    "wof:name":"Embouchure",
    "wof:placetype":"locality"
},
  "geometry": {"coordinates":[-63.01732,18.06386],"type":"Point"}
}