{
  "type": "Feature",
  "properties": {
    "gn:admin1_code":"0.0",
    "gn:asciiname":"Cul-de-Sac",
    "gn:country_code":"MF",
    "gn:dem":1,
    "gn:feature_class":"P",
    "gn:feature_code":"PPL",
    "gn:name":"Cul-de-Sac",
    "gn:population":0,
    "gn:timezone":"America/Marigot",
    "iso:country":"MF",
    "name:fra_x_preferred":[
        "Cul-de-Sac"
    ],
    "name:und_x_variant":[
        "Cul de Sac"
    ],
    "wof:name":"Cul-de-Sac",
    "wof:placetype":"locality"
},
  "geometry": {"coordinates":[-63.03032,18.10156],"type":"Point"}
}