{
  "type": "Feature",
  "properties": {
    "gn:admin1_code":"0.0",
    "gn:asciiname":"Griselle",
    "gn:country_code":"MF",
    "gn:dem":13,
    "gn:feature_class":"P",
    "gn:feature_code":"PPLL",
    "gn:name":"Griselle",
    "gn:population":0,
    "gn:timezone":"America/Marigot",
    "iso:country":"MF",
    "name:fra_x_preferred":[
        "Griselle"
    ],
    "wof:name":"Griselle",
    "wof:placetype":"locality"
},
  "geometry": {"coordinates":[-63.02612,18.08955],"type":"Point"}
}