{
  "type": "Feature",
  "properties": {
    "gn:admin1_code":"0.0",
    "gn:asciiname":"Baie Nettle",
    "gn:country_code":"MF",
    "gn:dem":4,
    "gn:elevation":"15.0",
    "gn:feature_class":"P",
    "gn:feature_code":"PPLL",
    "gn:name":"Baie Nettle",
    "gn:population":0,
    "gn:timezone":"America/Marigot",
    "iso:country":"MF",
    "name:fra_x_preferred":[
        "Baie Nettle"
    ],
    "wof:name":"Baie Nettle",
    "wof:placetype":"locality"
},
  "geometry": {"coordinates":[-63.11178,18.06191],"type":"Point"}
}