{
  "type": "Feature",
  "properties": {
    "gn:admin1_code":"0.0",
    "gn:asciiname":"Les Village de St. Martin",
    "gn:country_code":"MF",
    "gn:dem":10,
    "gn:feature_class":"P",
    "gn:feature_code":"PPLL",
    "gn:name":"Les Village de St. Martin",
    "gn:population":0,
    "gn:timezone":"America/Marigot",
    "iso:country":"MF",
    "name:fra_x_preferred":[
        "Les Village de St. Martin"
    ],
    "wof:name":"Les Village de St. Martin",
    "wof:placetype":"locality"
},
  "geometry": {"coordinates":[-63.07932,18.06954],"type":"Point"}
}