{
  "type": "Feature",
  "properties": {
    "gn:admin1_code":"0.0",
    "gn:asciiname":"Quartier D'Orleans Sud",
    "gn:country_code":"MF",
    "gn:dem":6,
    "gn:feature_class":"P",
    "gn:feature_code":"PPLL",
    "gn:name":"Quartier D\u2019Orleans Sud",
    "gn:population":0,
    "gn:timezone":"America/Marigot",
    "iso:country":"MF",
    "wof:name":"Quartier D'Orleans Sud",
    "wof:placetype":"locality"
},
  "geometry": {"coordinates":[-63.03354,18.06911],"type":"Point"}
}