{
  "type": "Feature",
  "properties": {
    "gn:admin1_code":"0.0",
    "gn:asciiname":"Cripple Gate",
    "gn:country_code":"MF",
    "gn:dem":1,
    "gn:feature_class":"P",
    "gn:feature_code":"PPL",
    "gn:name":"Cripple Gate",
    "gn:population":0,
    "gn:timezone":"America/Marigot",
    "iso:country":"MF",
    "name:fra_x_preferred":[
        "Cripple Gate"
    ],
    "wof:name":"Cripple Gate",
    "wof:placetype":"locality"
},
  "geometry": {"coordinates":[-63.07099,18.08072],"type":"Point"}
}