{
  "type": "Feature",
  "properties": {
    "gn:admin1_code":"0.0",
    "gn:asciiname":"Grand Fond",
    "gn:country_code":"MF",
    "gn:dem":30,
    "gn:feature_class":"P",
    "gn:feature_code":"PPLL",
    "gn:name":"Grand Fond",
    "gn:population":0,
    "gn:timezone":"America/Marigot",
    "iso:country":"MF",
    "wof:name":"Grand Fond",
    "wof:placetype":"locality"
},
  "geometry": {"coordinates":[-63.04333000000001,18.06099],"type":"Point"}
}