{
  "type": "Feature",
  "properties": {
    "gn:admin1_code":"0.0",
    "gn:asciiname":"Fond Mahaut",
    "gn:country_code":"MF",
    "gn:dem":125,
    "gn:feature_class":"P",
    "gn:feature_code":"PPLL",
    "gn:name":"Fond Mahaut",
    "gn:population":0,
    "gn:timezone":"America/Marigot",
    "iso:country":"MF",
    "wof:name":"Fond Mahaut",
    "wof:placetype":"locality"
},
  "geometry": {"coordinates":[-63.04645,18.07075],"type":"Point"}
}